CHANGES.txt
LICENSE.txt
MANIFEST.in
README.txt
setup.py
js/__init__.py
js.howler.egg-info/PKG-INFO
js.howler.egg-info/SOURCES.txt
js.howler.egg-info/dependency_links.txt
js.howler.egg-info/entry_points.txt
js.howler.egg-info/namespace_packages.txt
js.howler.egg-info/not-zip-safe
js.howler.egg-info/requires.txt
js.howler.egg-info/top_level.txt
js/howler/__init__.py
js/howler/test_howler.txt
js/howler/resources/howler.core.js
js/howler/resources/howler.core.min.js
js/howler/resources/howler.js
js/howler/resources/howler.min.js
js/howler/resources/howler.spatial.js
js/howler/resources/howler.spatial.min.js