Metadata-Version: 1.0
Name: js.howler
Version: 2.0.9
Summary: Fanstatic packaging of Howler
Home-page: UNKNOWN
Author: Fanstatic Developers
Author-email: fanstatic@googlegroups.com
License: BSD
Platform: UNKNOWN
